Metadata-Version: 1.1
Name: MathisN-Ex8-9
Version: 0.1
Summary: Effectue les 4 opérations élémentaires sur 2 complexes
Home-page: UNKNOWN
Author: Mathis
Author-email: mathis.nenach@cpe.fr
License: UNKNOWN
Platform: UNKNOWN
Classifier: Programming Language :: Python :: 3
